texbld/__init__.py
texbld/cli/__init__.py
texbld/cli/cli.py
texbld/cli/getsha256.py
texbld/cli/project.py
texbld/cli/resource.py
texbld/cli/scaffold.py
texbld/cli/validate.py
texbld/clients/__init__.py
texbld/clients/client.py
texbld/clients/fs.py
texbld/clients/github.py
texbld/clients/local.py
texbld/common/__init__.py
texbld/common/image/__init__.py
texbld/common/image/image.py
texbld/common/image/parse.py
texbld/common/image/sourceimage.py
texbld/common/project/__init__.py
texbld/common/project/parse.py
texbld/common/project/project.py
texbld/common/solver.py
texbld/config.py
texbld/directory.py
texbld/docker/__init__.py
texbld/docker/build.py
texbld/docker/client.py
texbld/docker/dockergen.py
texbld/exceptions.py
texbld/globals.py
texbld/logger.py
texbld/parser/__init__.py
texbld/parser/v1/__init__.py
texbld/parser/v1/image.py
texbld/parser/v1/image_schema.json
texbld/parser/v1/project.py
texbld/parser/v1/project_schema.json
texbld/scaffold/__init__.py
texbld/scaffold/copy.py
texbld/scaffold/project.py
texbld/scaffold/sample_image.toml
texbld/scaffold/scaffold.py
texbld/scaffold/validate.py
texbld/utils/__init__.py
texbld/utils/github.py
texbld/utils/search.py
texbld-0.4.1.dist-info/entry_points.txt
texbld-0.4.1.dist-info/LICENSE.md
texbld-0.4.1.dist-info/WHEEL
texbld-0.4.1.dist-info/METADATA
texbld-0.4.1.dist-info/RECORD
