Metadata-Version: 2.1
Name: texbld
Version: 0.4.1
Summary: A dockerized build tool for paper compilation
Home-page: https://github.com/texbld/texbld
License: GPL-3.0-or-later
Keywords: reproducibility,docker,LaTeX
Author: junikimm717
Author-email: junikimm717@gmail.com
Requires-Python: >=3.9,<4.0
Classifier: License :: OSI Approved :: GNU General Public License v3 or later (GPLv3+)
Classifier: Programming Language :: Python :: 3
Classifier: Programming Language :: Python :: 3.10
Classifier: Programming Language :: Python :: 3.9
Classifier: Topic :: Software Development :: Build Tools
Classifier: Topic :: Software Development :: Libraries :: Python Modules
Requires-Dist: docker (>=5.0.3,<6.0.0)
Requires-Dist: jsonschema (>=4.5.1,<5.0.0)
Requires-Dist: toml (>=0.10.2,<0.11.0)
Requires-Dist: urllib3 (>=1.26.9,<2.0.0)
Project-URL: Repository, https://github.com/texbld/texbld
